raksha_logger/__init__.py
raksha_logger/main.py
raksha_logger-1.0.1.dist-info/METADATA
raksha_logger-1.0.1.dist-info/WHEEL
raksha_logger-1.0.1.dist-info/top_level.txt
raksha_logger-1.0.1.dist-info/RECORD
