Metadata-Version: 2.1
Name: raksha-logger
Version: 1.0.1
Summary: A custom logger with colored log levels and caller file information
Home-page: UNKNOWN
Author: Raksha
Author-email: rakshakarnofficial@gmail.com
License: UNKNOWN
Platform: UNKNOWN
Classifier: Programming Language :: Python :: 3
Classifier: License :: OSI Approved :: MIT License
Classifier: Operating System :: OS Independent
Requires-Python: >=3.6
